{
    "gitignore.nix": {
        "branch": "master",
        "description": "Nix functions for filtering local git sources",
        "homepage": "",
        "owner": "hercules-ci",
        "repo": "gitignore.nix",
        "rev": "bff2832ec341cf30acb3a4d3e2e7f1f7b590116a",
        "sha256": "0va0janxvmilm67nbl81gdbpppal4aprxzb25gp9pqvf76ahxsci",
        "type": "tarball",
        "url": "https://github.com/hercules-ci/gitignore.nix/archive/bff2832ec341cf30acb3a4d3e2e7f1f7b590116a.tar.gz",
        "url_template": "https://github.com/<owner>/<repo>/archive/<rev>.tar.gz"
    },
    "nixpkgs": {
        "branch": "nixos-unstable-small",
        "description": "Nix Packages collection",
        "homepage": "",
        "owner": "NixOS",
        "repo": "nixpkgs",
        "rev": "e2a1802777ecddcd3fce0d3d066cf8fc8c481dc9",
        "sha256": "1c201db3h7zmhxvrsysgfcg7ki9hv101pjd9ai9ryg7na55nwh2s",
        "type": "tarball",
        "url": "https://github.com/NixOS/nixpkgs/archive/e2a1802777ecddcd3fce0d3d066cf8fc8c481dc9.tar.gz",
        "url_template": "https://github.com/<owner>/<repo>/archive/<rev>.tar.gz"
    },
    "poetry2nix": {
        "branch": "master",
        "description": "Convert poetry projects to nix automagically [maintainer=@adisbladis] ",
        "homepage": "",
        "owner": "nix-community",
        "repo": "poetry2nix",
        "rev": "3769e0c1f62246c399fa4a8dbb6c7a4a421f1127",
        "sha256": "15ha7i3bm1knh4cg1w2ra70q1k0yi1rd03qisagv3dkghigvy959",
        "type": "tarball",
        "url": "https://github.com/nix-community/poetry2nix/archive/3769e0c1f62246c399fa4a8dbb6c7a4a421f1127.tar.gz",
        "url_template": "https://github.com/<owner>/<repo>/archive/<rev>.tar.gz"
    }
}
