{"add":{"path":"59-72bab529-334a-45c8-b5c2-4d5690f85890-0.parquet","size":6194,"partitionValues":{},"modificationTime":1691805771729,"dataChange":true,"stats":"{\"numRecords\": 344, \"minValues\": {\"species\": \"Adelie\", \"island\": \"Biscoe\", \"bill_length_mm\": 32.1, \"bill_depth_mm\": 13.1, \"flipper_length_mm\": 172, \"body_mass_g\": 2700, \"sex\": \"female\", \"year\": 2007}, \"maxValues\": {\"species\": \"Gentoo\", \"island\": \"Torgersen\", \"bill_length_mm\": 59.6, \"bill_depth_mm\": 21.5, \"flipper_length_mm\": 231, \"body_mass_g\": 6300, \"sex\": \"male\", \"year\": 2009}, \"nullCount\": {\"species\": 0, \"island\": 0, \"bill_length_mm\": 2, \"bill_depth_mm\": 2, \"flipper_length_mm\": 2, \"body_mass_g\": 2, \"sex\": 11, \"year\": 0}}","tags":null}}
{"remove":{"path":"58-de87487d-ad0d-4c78-b669-263f7269d55a-0.parquet","deletionTimestamp":1691805771729,"dataChange":true,"extendedFileMetadata":false,"partitionValues":{},"size":6194,"tags":null}}
{"commitInfo":{"timestamp":1691805771729,"operation":"WRITE","operationParameters":{"partitionBy":"[]","mode":"Overwrite"},"clientVersion":"delta-rs.0.13.1"}}